Workbook

Sheet ReadMe - Validator Instructions
A1: Equity Value Creation Bridge Toolkit - v1.0
A2: Post Fiat Analytical Infrastructure Library | Reusable LMM private equity workflow | Formula-driven, anonymized
A4: Purpose
A5: Bridges sponsor entry equity to exit equity across seven levers: organic revenue growth, add-on revenue, margin change, multiple change, add-on purchase price, debt paydown and cash generation. It then ranks the levers, tests reliance on multiple expansion, runs a downside case and returns one underwriting recommendation.
A7: How to use
A8: 1. Enter deal inputs (yellow cells) on Entry and Exit Assumptions B5:B24 and Value Driver Inputs B4:B18.
A9: 2. Check that Equity Value Creation Bridge E16 reads 'OK - bridge reconciles' and Value Driver Inputs B30 reads 'OK'.
A10: 3. Read the lever ranking and reliance tests, then the recommendation in Summary Recommendation B27 and its reasoning in B28.
A11: 4. Record each non-obvious underwriting choice as a named judgment call (see Anonymized Worked Example rows 26-29).
A13: Tabs
A14: # | B14: Tab | C14: What it does
A15: 1 | B15: ReadMe - Validator Instructions | C15: Purpose, usage and validator checklist
A16: 2 | B16: Entry and Exit Assumptions | C16: Entry valuation, exit multiple, return targets and downside settings
A17: 3 | B17: Value Driver Inputs | C17: Operating levers and the annual EBITDA / FCF schedule
A18: 4 | B18: Equity Value Creation Bridge | C18: Seven-step additive bridge with reconciliation and FORMULATEXT
A19: 5 | B19: Lever Impact Ranking | C19: Lever ranking, categories and reliance tests
A20: 6 | B20: Summary Recommendation | C20: Base and downside returns gated into one recommendation
A21: 7 | B21: Anonymized Worked Example | C21: HoldCo B example: bridge output, chart, 4 named judgment calls, result
A23: Colour legend: yellow = input, blue = formula, green = key output. Tab 1 is named 'ReadMe - Validator Instructions' because Excel does not allow '/' in tab names.
A25: Validator checklist (criterion -> tab -> cell range -> live check)
A26: # | B26: Criterion | C26: Tab | D26: Cell range | E26: Live check
A27: 1 | B27: Bridge from entry equity to exit equity, all live formulas | C27: Equity Value Creation Bridge | D27: D4:D12; FORMULATEXT in F4:F19 | E27: ='Equity Value Creation Bridge'!E16 -> OK - bridge reconciles
A28: 2 | B28: Levers: EBITDA growth (organic + add-on), margin, multiple, debt paydown, cash generation | C28: Equity Value Creation Bridge | D28: B5:E11 | E28: =COUNTA('Equity Value Creation Bridge'!B5:B11)&" levers" -> 7 levers
A29: 3 | B29: Bridge reconciles to directly computed exit equity | C29: Equity Value Creation Bridge | D29: D13:D16; status E16 | E29: =TEXT('Equity Value Creation Bridge'!D16,"0.000000") -> 0.000000
A30: 4 | B30: Annual EBITDA / FCF schedule covers the hold period | C30: Value Driver Inputs | D30: A22:F30; status B30 | E30: ='Value Driver Inputs'!B30 -> OK
A31: 5 | B31: Lever ranking and reliance tests | C31: Lever Impact Ranking | D31: A4:F10; A14:D20 | E31: ='Lever Impact Ranking'!D17&" | "&'Lever Impact Ranking'!D18 -> PASS - at or above minimum | PASS - at or below maximum
A32: 6 | B32: Clear recommendation with visible logic | C32: Summary Recommendation | D32: B27 (formula text in B29); reasoning B28 | E32: ='Summary Recommendation'!B27 -> UNDERWRITE - VALUE CREATION PLAN SUPPORTS RETURNS
A33: 7 | B33: Anonymized worked example with visible bridge output | C33: Anonymized Worked Example | D33: A14:C22 plus bar chart | E33: ="Exit equity $"&TEXT('Anonymized Worked Example'!B22,"0.00")&"M" -> Exit equity $110.13M
A34: 8 | B34: At least 3 named judgment calls | C34: Anonymized Worked Example | D34: A26:F29 | E34: =COUNTA('Anonymized Worked Example'!A26:A29)&" judgment calls" -> 4 judgment calls
A35: 9 | B35: Zero formula errors | C35: All tabs | D35: Excel SpecialCells(xlFormulas, xlErrors) scan | E35: See README.md (recalculated in Excel)

Sheet Entry and Exit Assumptions
A1: Entry and Exit Assumptions
A2: Yellow = input, blue = formula. $M unless noted. Change inputs here and on Value Driver Inputs; every other tab recalculates.
A3: Input | B3: Value | C3: Unit | D3: Source / note
A4: Deal code name | B4: HoldCo B (anonymized) | C4: text | D4: Code name only; no company identifiers.
A5: Entry LTM revenue | B5: 60 | C5: $M | D5: Scaled, illustrative LMM services platform.
A6: Entry EBITDA margin | B6: 0.15 | C6: % | D6: Quality-of-earnings adjusted.
A7: Entry LTM EBITDA | B7: =B5*B6 -> 9 | C7: $M | D7: Revenue x margin.
A8: Entry EV / EBITDA multiple | B8: 8 | C8: x | D8: Purchase multiple paid.
A9: Entry enterprise value | B9: =B7*B8 -> 72 | C9: $M | D9: EBITDA x multiple.
A10: Entry net debt | B10: 40 | C10: $M | D10: Acquisition debt less closing cash.
A11: Entry leverage (net debt / EBITDA) | B11: =B10/B7 -> 4.4444444 | C11: x | D11: Sanity check vs lender appetite.
A12: Entry equity value | B12: =B9-B10 -> 32 | C12: $M | D12: Sponsor equity cheque (fees ignored).
A13: Hold period | B13: 5 | C13: yrs | D13: Whole years, 1-7 (schedule supports up to 7).
A14: Underwritten exit EV / EBITDA multiple | B14: 8 | C14: x | D14: Judgment call JC1: held flat at entry multiple.
A15: Management-case exit multiple (reference only) | B15: 9.5 | C15: x | D15: Not underwritten; sizes JC1.
A16: Target gross MOIC | B16: 2.5 | C16: x | D16: Fund underwriting hurdle.
A17: Target gross IRR | B17: 0.2 | C17: % | D17: Fund underwriting hurdle.
A18: Base-case MOIC floor | B18: 1.75 | C18: x | D18: Below this, do not underwrite.
A19: Downside-case MOIC floor | B19: 1.25 | C19: x | D19: Capital-preservation test.
A20: Max share of value created from multiple change | B20: 0.25 | C20: % | D20: Limits reliance on market re-rating.
A21: Min share of value created from operational levers | B21: 0.5 | C21: % | D21: Organic growth + add-on + margin.
A22: Downside: exit multiple haircut | B22: 1 | C22: x | D22: Turns below underwritten exit multiple.
A23: Downside: organic growth credited | B23: 0.5 | C23: % | D23: Share of base organic CAGR achieved.
A24: Downside: margin change credited | B24: 0 | C24: % | D24: Share of base margin change achieved.

Sheet Value Driver Inputs
A1: Value Driver Inputs
A2: Operating and financial levers over the hold period, plus the annual EBITDA / free cash flow schedule.
A3: Driver | B3: Value | C3: Unit | D3: Source / note
A4: Organic revenue CAGR | B4: 0.06 | C4: % | D4: Price + volume; excludes add-ons.
A5: Organic exit revenue | B5: ='Entry and Exit Assumptions'!B5*(1+B4)^'Entry and Exit Assumptions'!B13 -> 80.293535 | C5: $M | D5: Entry revenue compounded over the hold.
A6: Add-on revenue acquired (run-rate at exit) | B6: 12 | C6: $M | D6: JC3: one signed-LOI add-on only.
A7: Add-on EBITDA margin at acquisition | B7: 0.12 | C7: % | D7: Pre-synergy margin of the add-on.
A8: Add-on purchase multiple | B8: 5.5 | C8: x | D8: Multiple arbitrage vs platform entry multiple.
A9: Add-on purchase price (debt-funded) | B9: =B6*B7*B8 -> 7.92 | C9: $M | D9: Funded with incremental debt.
A10: Exit revenue | B10: =B5+B6 -> 92.293535 | C10: $M | D10: Organic + add-on.
A11: Exit EBITDA margin | B11: 0.17 | C11: % | D11: JC2: +200 bps credited of a +400 bps plan.
A12: Exit EBITDA | B12: =B10*B11 -> 15.689901 | C12: $M | D12: Exit revenue x exit margin.
A13: Margin change vs entry | B13: =(B11-'Entry and Exit Assumptions'!B6)*10000 -> 200 | C13: bps | D13: Basis points.
A14: Cash conversion (FCF / EBITDA) | B14: 0.5 | C14: % | D14: JC4: after capex, cash tax and interest.
A15: Share of FCF swept to debt paydown | B15: 0.8 | C15: % | D15: Remainder retained as balance-sheet cash.
A16: Management-case exit margin (reference only) | B16: 0.19 | C16: % | D16: Not underwritten; sizes JC2.
A17: Management-case cash conversion (reference only) | B17: 0.65 | C17: % | D17: Not underwritten; sizes JC4.
A18: Add-on pipeline revenue excluded (reference only) | B18: 20 | C18: $M | D18: Two unsigned targets; sizes JC3.
A20: Annual EBITDA and free cash flow schedule (linear EBITDA path from entry to exit)
A21: Year | B21: In hold? (1/0) | C21: EBITDA ($M) | D21: Free cash flow ($M) | E21: Debt paydown ($M) | F21: Cash retained ($M)
A22: 1 | B22: =IF(A22<='Entry and Exit Assumptions'!$B$13,1,0) -> 1 | C22: =B22*('Entry and Exit Assumptions'!$B$7+($B$12-'Entry and Exit Assumptions'!$B$7)*A22/'Entry and Exit Assumptions'!$B$13) -> 10.33798 | D22: =C22*$B$14 -> 5.1689901 | E22: =D22*$B$15 -> 4.1351921 | F22: =D22-E22 -> 1.033798
A23: 2 | B23: =IF(A23<='Entry and Exit Assumptions'!$B$13,1,0) -> 1 | C23: =B23*('Entry and Exit Assumptions'!$B$7+($B$12-'Entry and Exit Assumptions'!$B$7)*A23/'Entry and Exit Assumptions'!$B$13) -> 11.67596 | D23: =C23*$B$14 -> 5.8379802 | E23: =D23*$B$15 -> 4.6703841 | F23: =D23-E23 -> 1.167596
A24: 3 | B24: =IF(A24<='Entry and Exit Assumptions'!$B$13,1,0) -> 1 | C24: =B24*('Entry and Exit Assumptions'!$B$7+($B$12-'Entry and Exit Assumptions'!$B$7)*A24/'Entry and Exit Assumptions'!$B$13) -> 13.013941 | D24: =C24*$B$14 -> 6.5069703 | E24: =D24*$B$15 -> 5.2055762 | F24: =D24-E24 -> 1.3013941
A25: 4 | B25: =IF(A25<='Entry and Exit Assumptions'!$B$13,1,0) -> 1 | C25: =B25*('Entry and Exit Assumptions'!$B$7+($B$12-'Entry and Exit Assumptions'!$B$7)*A25/'Entry and Exit Assumptions'!$B$13) -> 14.351921 | D25: =C25*$B$14 -> 7.1759604 | E25: =D25*$B$15 -> 5.7407683 | F25: =D25-E25 -> 1.4351921
A26: 5 | B26: =IF(A26<='Entry and Exit Assumptions'!$B$13,1,0) -> 1 | C26: =B26*('Entry and Exit Assumptions'!$B$7+($B$12-'Entry and Exit Assumptions'!$B$7)*A26/'Entry and Exit Assumptions'!$B$13) -> 15.689901 | D26: =C26*$B$14 -> 7.8449504 | E26: =D26*$B$15 -> 6.2759604 | F26: =D26-E26 -> 1.5689901
A27: 6 | B27: =IF(A27<='Entry and Exit Assumptions'!$B$13,1,0) -> 0 | C27: =B27*('Entry and Exit Assumptions'!$B$7+($B$12-'Entry and Exit Assumptions'!$B$7)*A27/'Entry and Exit Assumptions'!$B$13) -> 0 | D27: =C27*$B$14 -> 0 | E27: =D27*$B$15 -> 0 | F27: =D27-E27 -> 0
A28: 7 | B28: =IF(A28<='Entry and Exit Assumptions'!$B$13,1,0) -> 0 | C28: =B28*('Entry and Exit Assumptions'!$B$7+($B$12-'Entry and Exit Assumptions'!$B$7)*A28/'Entry and Exit Assumptions'!$B$13) -> 0 | D28: =C28*$B$14 -> 0 | E28: =D28*$B$15 -> 0 | F28: =D28-E28 -> 0
A29: Total | B29: =SUM(B22:B28) -> 5 | C29: =SUM(C22:C28) -> 65.069703 | D29: =SUM(D22:D28) -> 32.534851 | E29: =SUM(E22:E28) -> 26.027881 | F29: =SUM(F22:F28) -> 6.5069703
A30: Check: years modelled = hold period | B30: =IF(B29='Entry and Exit Assumptions'!B13,"OK","ERROR - hold must be 1-7 years") -> OK

Sheet Equity Value Creation Bridge
A1: Equity Value Creation Bridge
A2: Entry equity -> exit equity. Every step is a live formula; the additive bridge must reconcile to directly computed exit equity.
A3: Step | B3: Lever | C3: Logic | D3: Value ($M) | E3: % of value created | F3: Live formula (FORMULATEXT)
A4: Start | B4: Entry equity value | C4: Entry EV less entry net debt | D4: ='Entry and Exit Assumptions'!B12 -> 32 | F4: =_xlfn.FORMULATEXT(D4) -> ='Entry and Exit Assumptions'!B12
A5: Step 1 | B5: Organic revenue growth | C5: (Organic exit revenue - entry revenue) x entry margin x entry multiple | D5: =('Value Driver Inputs'!B5-'Entry and Exit Assumptions'!B5)*'Entry and Exit Assumptions'!B6*'Entry and Exit Assumptions'!B8 -> 24.352242 | E5: =IFERROR(D5/$D$17,0) -> 0.31167255 | F5: =_xlfn.FORMULATEXT(D5) -> =('Value Driver Inputs'!B5-'Entry and Exit Assumptions'!B5)*'Entry and Exit Assumptions'!B6*'Entry and Exit Assumptions'!B8
A6: Step 2 | B6: Add-on revenue | C6: Add-on revenue x entry margin x entry multiple | D6: ='Value Driver Inputs'!B6*'Entry and Exit Assumptions'!B6*'Entry and Exit Assumptions'!B8 -> 14.4 | E6: =IFERROR(D6/$D$17,0) -> 0.18429863 | F6: =_xlfn.FORMULATEXT(D6) -> ='Value Driver Inputs'!B6*'Entry and Exit Assumptions'!B6*'Entry and Exit Assumptions'!B8
A7: Step 3 | B7: Margin change | C7: Exit revenue x (exit margin - entry margin) x entry multiple | D7: ='Value Driver Inputs'!B10*('Value Driver Inputs'!B11-'Entry and Exit Assumptions'!B6)*'Entry and Exit Assumptions'!B8 -> 14.766966 | E7: =IFERROR(D7/$D$17,0) -> 0.18899525 | F7: =_xlfn.FORMULATEXT(D7) -> ='Value Driver Inputs'!B10*('Value Driver Inputs'!B11-'Entry and Exit Assumptions'!B6)*'Entry and Exit Assumptions'!B8
A8: Step 4 | B8: Multiple change | C8: Exit EBITDA x (exit multiple - entry multiple) | D8: ='Value Driver Inputs'!B12*('Entry and Exit Assumptions'!B14-'Entry and Exit Assumptions'!B8) -> 0 | E8: =IFERROR(D8/$D$17,0) -> 0 | F8: =_xlfn.FORMULATEXT(D8) -> ='Value Driver Inputs'!B12*('Entry and Exit Assumptions'!B14-'Entry and Exit Assumptions'!B8)
A9: Step 5 | B9: Add-on purchase price (debt-funded) | C9: Incremental debt raised to buy the add-on | D9: =-'Value Driver Inputs'!B9 -> -7.92 | E9: =IFERROR(D9/$D$17,0) -> -0.10136425 | F9: =_xlfn.FORMULATEXT(D9) -> =-'Value Driver Inputs'!B9
A10: Step 6 | B10: Debt paydown | C10: Cumulative FCF swept to debt | D10: ='Value Driver Inputs'!E29 -> 26.027881 | E10: =IFERROR(D10/$D$17,0) -> 0.33311825 | F10: =_xlfn.FORMULATEXT(D10) -> ='Value Driver Inputs'!E29
A11: Step 7 | B11: Cash generation (retained) | C11: Cumulative FCF retained as cash | D11: ='Value Driver Inputs'!F29 -> 6.5069703 | E11: =IFERROR(D11/$D$17,0) -> 0.083279563 | F11: =_xlfn.FORMULATEXT(D11) -> ='Value Driver Inputs'!F29
A12: End | B12: Exit equity value (bridge) | C12: Entry equity + steps 1-7 | D12: =D4+SUM(D5:D11) -> 110.13406 | F12: =_xlfn.FORMULATEXT(D12) -> =D4+SUM(D5:D11)
A13: Check | B13: Exit enterprise value (direct) | C13: Exit EBITDA x exit multiple | D13: ='Value Driver Inputs'!B12*'Entry and Exit Assumptions'!B14 -> 125.51921 | F13: =_xlfn.FORMULATEXT(D13) -> ='Value Driver Inputs'!B12*'Entry and Exit Assumptions'!B14
A14: Check | B14: Exit net debt (direct) | C14: Entry net debt + add-on debt - cumulative FCF | D14: ='Entry and Exit Assumptions'!B10+'Value Driver Inputs'!B9-'Value Driver Inputs'!D29 -> 15.385149 | F14: =_xlfn.FORMULATEXT(D14) -> ='Entry and Exit Assumptions'!B10+'Value Driver Inputs'!B9-'Value Driver Inputs'!D29
A15: Check | B15: Exit equity value (direct) | C15: Exit EV - exit net debt | D15: =D13-D14 -> 110.13406 | F15: =_xlfn.FORMULATEXT(D15) -> =D13-D14
A16: Check | B16: Bridge minus direct (must be 0) | C16: Reconciles the additive bridge to the direct calculation | D16: =ROUND(D12-D15,6) -> 0 | E16: =IF(ABS(D16)<0.001,"OK - bridge reconciles","ERROR - bridge does not reconcile") -> OK - bridge reconciles | F16: =_xlfn.FORMULATEXT(D16) -> =ROUND(D12-D15,6)
A17: Result | B17: Total value created | C17: Exit equity - entry equity | D17: =D12-D4 -> 78.134058 | F17: =_xlfn.FORMULATEXT(D17) -> =D12-D4
A18: Result | B18: Gross MOIC | C18: Exit equity / entry equity | D18: =D12/D4 -> 3.4416893 | F18: =_xlfn.FORMULATEXT(D18) -> =D12/D4
A19: Result | B19: Gross IRR | C19: MOIC^(1/hold) - 1 (single entry and exit cash flow) | D19: =D18^(1/'Entry and Exit Assumptions'!B13)-1 -> 0.28042555 | F19: =_xlfn.FORMULATEXT(D19) -> =D18^(1/'Entry and Exit Assumptions'!B13)-1

Sheet Lever Impact Ranking
A1: Lever Impact Ranking
A2: Ranks bridge levers by equity value contribution and tests reliance on market vs operational levers.
A3: Lever | B3: Category | C3: Value ($M) | D3: % of value created | E3: Rank (1 = largest) | F3: Controllability
A4: ='Equity Value Creation Bridge'!B5 -> Organic revenue growth | B4: Operational | C4: ='Equity Value Creation Bridge'!D5 -> 24.352242 | D4: ='Equity Value Creation Bridge'!E5 -> 0.31167255 | E4: =RANK(C4,$C$4:$C$10,0) -> 2 | F4: High - pricing, sales capacity, retention
A5: ='Equity Value Creation Bridge'!B6 -> Add-on revenue | B5: Operational | C5: ='Equity Value Creation Bridge'!D6 -> 14.4 | D5: ='Equity Value Creation Bridge'!E6 -> 0.18429863 | E5: =RANK(C5,$C$4:$C$10,0) -> 4 | F5: Medium - depends on signing and closing add-ons
A6: ='Equity Value Creation Bridge'!B7 -> Margin change | B6: Operational | C6: ='Equity Value Creation Bridge'!D7 -> 14.766966 | D6: ='Equity Value Creation Bridge'!E7 -> 0.18899525 | E6: =RANK(C6,$C$4:$C$10,0) -> 3 | F6: High - procurement, labor productivity, pricing
A7: ='Equity Value Creation Bridge'!B8 -> Multiple change | B7: Market | C7: ='Equity Value Creation Bridge'!D8 -> 0 | D7: ='Equity Value Creation Bridge'!E8 -> 0 | E7: =RANK(C7,$C$4:$C$10,0) -> 6 | F7: Low - exit market conditions
A8: ='Equity Value Creation Bridge'!B9 -> Add-on purchase price (debt-funded) | B8: Financial | C8: ='Equity Value Creation Bridge'!D9 -> -7.92 | D8: ='Equity Value Creation Bridge'!E9 -> -0.10136425 | E8: =RANK(C8,$C$4:$C$10,0) -> 7 | F8: Medium - negotiated add-on purchase multiple
A9: ='Equity Value Creation Bridge'!B10 -> Debt paydown | B9: Financial | C9: ='Equity Value Creation Bridge'!D10 -> 26.027881 | D9: ='Equity Value Creation Bridge'!E10 -> 0.33311825 | E9: =RANK(C9,$C$4:$C$10,0) -> 1 | F9: High - follows cash conversion and sweep
A10: ='Equity Value Creation Bridge'!B11 -> Cash generation (retained) | B10: Financial | C10: ='Equity Value Creation Bridge'!D11 -> 6.5069703 | D10: ='Equity Value Creation Bridge'!E11 -> 0.083279563 | E10: =RANK(C10,$C$4:$C$10,0) -> 5 | F10: High - follows cash conversion
A12: Lever reliance tests
A13: Test | B13: Value | C13: Threshold | D13: Status
A14: Operational levers ($M) | B14: =SUMIF(B4:B10,"Operational",C4:C10) -> 53.519207
A15: Market levers ($M) | B15: =SUMIF(B4:B10,"Market",C4:C10) -> 0
A16: Financial levers ($M) | B16: =SUMIF(B4:B10,"Financial",C4:C10) -> 24.614851
A17: Operational share of value created | B17: =IFERROR(B14/'Equity Value Creation Bridge'!D17,0) -> 0.68496643 | C17: ='Entry and Exit Assumptions'!B21 -> 0.5 | D17: =IF(B17>=C17,"PASS - at or above minimum","FAIL - below minimum") -> PASS - at or above minimum
A18: Multiple-change share of value created | B18: =IFERROR(B15/'Equity Value Creation Bridge'!D17,0) -> 0 | C18: ='Entry and Exit Assumptions'!B20 -> 0.25 | D18: =IF(B18<=C18,"PASS - at or below maximum","FAIL - above maximum") -> PASS - at or below maximum
A19: Largest lever | B19: =INDEX(A4:A10,MATCH(1,E4:E10,0)) -> Debt paydown
A20: Largest lever share of value created | B20: =INDEX(D4:D10,MATCH(1,E4:E10,0)) -> 0.33311825

Sheet Summary Recommendation
A1: Summary Recommendation
A2: Gates base-case returns, lever reliance and a downside case into one underwriting recommendation.
A3: Metric | B3: Value | C3: Note
A4: Entry equity value | B4: ='Equity Value Creation Bridge'!D4 -> 32 | C4: Bridge D4
A5: Exit equity value | B5: ='Equity Value Creation Bridge'!D12 -> 110.13406 | C5: Bridge D12
A6: Total value created | B6: ='Equity Value Creation Bridge'!D17 -> 78.134058 | C6: Bridge D17
A7: Gross MOIC | B7: ='Equity Value Creation Bridge'!D18 -> 3.4416893 | C7: Bridge D18
A8: Gross IRR | B8: ='Equity Value Creation Bridge'!D19 -> 0.28042555 | C8: Bridge D19
A9: Target gross MOIC | B9: ='Entry and Exit Assumptions'!B16 -> 2.5 | C9: Input
A10: Target gross IRR | B10: ='Entry and Exit Assumptions'!B17 -> 0.2 | C10: Input
A11: Operational share of value created | B11: ='Lever Impact Ranking'!B17 -> 0.68496643 | C11: Lever Impact Ranking B17
A12: Minimum operational share | B12: ='Entry and Exit Assumptions'!B21 -> 0.5 | C12: Input
A13: Multiple-change share of value created | B13: ='Lever Impact Ranking'!B18 -> 0 | C13: Lever Impact Ranking B18
A14: Maximum multiple-change share | B14: ='Entry and Exit Assumptions'!B20 -> 0.25 | C14: Input
A15: Downside case (stress test)
A16: Downside organic exit revenue | B16: ='Entry and Exit Assumptions'!B5*(1+'Value Driver Inputs'!B4*'Entry and Exit Assumptions'!B23)^'Entry and Exit Assumptions'!B13 -> 69.556444 | C16: Organic CAGR x growth credited
A17: Downside exit EBITDA margin | B17: ='Entry and Exit Assumptions'!B6+('Value Driver Inputs'!B11-'Entry and Exit Assumptions'!B6)*'Entry and Exit Assumptions'!B24 -> 0.15 | C17: Entry margin + credited margin change
A18: Downside exit EBITDA | B18: =(B16+'Value Driver Inputs'!B6)*B17 -> 12.233467 | C18: Signed add-on revenue retained
A19: Downside exit multiple | B19: ='Entry and Exit Assumptions'!B14-'Entry and Exit Assumptions'!B22 -> 7 | C19: Underwritten exit multiple less haircut
A20: Downside cumulative FCF | B20: ='Value Driver Inputs'!B14*('Entry and Exit Assumptions'!B13*'Entry and Exit Assumptions'!B7+(B18-'Entry and Exit Assumptions'!B7)*('Entry and Exit Assumptions'!B13+1)/2) -> 27.3502 | C20: Same linear EBITDA path as the schedule
A21: Downside exit net debt | B21: ='Entry and Exit Assumptions'!B10+'Value Driver Inputs'!B9-B20 -> 20.5698 | C21: Entry net debt + add-on debt - FCF
A22: Downside exit equity value | B22: =B18*B19-B21 -> 65.064467 | C22: Downside EV - downside net debt
A23: Downside MOIC | B23: =B22/B4 -> 2.0332646 | C23: Downside exit equity / entry equity
A24: Downside MOIC floor | B24: ='Entry and Exit Assumptions'!B19 -> 1.25 | C24: Input
A25: Base-case MOIC floor | B25: ='Entry and Exit Assumptions'!B18 -> 1.75 | C25: Input
A26: Bridge reconciliation | B26: ='Equity Value Creation Bridge'!E16 -> OK - bridge reconciles | C26: Bridge E16
A27: RECOMMENDATION | B27: =IF(B26<>"OK - bridge reconciles","CHECK MODEL - BRIDGE DOES NOT RECONCILE",IF(OR(B7<B25,B23<B24),"DO NOT UNDERWRITE AT CURRENT TERMS",IF(AND(B7>=B9,B8>=B10,B11>=B12,B13<=B14),"UNDERWRITE - VALUE CREATION PLAN SUPPORTS RETURNS","UNDERWRITE WITH CONDITIONS - REBALANCE LEVER RELIANCE"))) -> UNDERWRITE - VALUE CREATION PLAN SUPPORTS RETURNS | C27: Order: reconciliation -> floors (base and downside) -> targets and lever-reliance tests.
A28: Reasoning | B28: ="Base MOIC "&TEXT(B7,"0.00")&"x vs target "&TEXT(B9,"0.00")&"x; IRR "&TEXT(B8,"0.0%")&" vs "&TEXT(B10,"0.0%")&"; operational share "&TEXT(B11,"0%")&" (min "&TEXT(B12,"0%")&"); multiple share "&TEXT(B13,"0%")&" (max "&TEXT(B14,"0%")&"); downside MOIC "&TEXT(B23,"0.00")&"x (floor "&TEXT(B24,"0.00")&"x)." -> Base MOIC 3.44x vs target 2.50x; IRR 28.0% vs 20.0%; operational share 68% (min 50%); multiple share 0% (max 25%); downside MOIC 2.03x (floor 1.25x).
A29: Recommendation formula (FORMULATEXT of B27) | B29: =_xlfn.FORMULATEXT(B27) -> =IF(B26<>"OK - bridge reconciles","CHECK MODEL - BRIDGE DOES NOT RECONCILE",IF(OR(B7<B25,B23<B24),"DO NOT UNDERWRITE AT CURRENT TERMS",IF(AND(B7>=B9,B8>=B10,B11>=B12,B13<=B14),"UNDERWRITE - VALUE CREATION PLAN SUPPORTS RETURNS","UNDERWRITE WITH CONDITIONS - REBALANCE LEVER RELIANCE")))

Sheet Anonymized Worked Example
A1: Anonymized Worked Example - HoldCo B
A2: Regional industrial services platform (code name). Figures scaled and illustrative; every output is a live link to the model tabs.
A3: Deal snapshot
A4: Item | B4: Value | C4: Unit
A5: Entry LTM EBITDA | B5: ='Entry and Exit Assumptions'!B7 -> 9 | C5: $M
A6: Entry EV / EBITDA multiple | B6: ='Entry and Exit Assumptions'!B8 -> 8 | C6: x
A7: Entry equity value | B7: ='Entry and Exit Assumptions'!B12 -> 32 | C7: $M
A8: Exit EBITDA | B8: ='Value Driver Inputs'!B12 -> 15.689901 | C8: $M
A9: Underwritten exit multiple | B9: ='Entry and Exit Assumptions'!B14 -> 8 | C9: x
A10: Hold period | B10: ='Entry and Exit Assumptions'!B13 -> 5 | C10: yrs
A12: Bridge output: entry equity -> exit equity ($M)
A13: Bridge step | B13: Value ($M) | C13: % of value created
A14: ='Equity Value Creation Bridge'!B4 -> Entry equity value | B14: ='Equity Value Creation Bridge'!D4 -> 32
A15: ='Equity Value Creation Bridge'!B5 -> Organic revenue growth | B15: ='Equity Value Creation Bridge'!D5 -> 24.352242 | C15: ='Equity Value Creation Bridge'!E5 -> 0.31167255
A16: ='Equity Value Creation Bridge'!B6 -> Add-on revenue | B16: ='Equity Value Creation Bridge'!D6 -> 14.4 | C16: ='Equity Value Creation Bridge'!E6 -> 0.18429863
A17: ='Equity Value Creation Bridge'!B7 -> Margin change | B17: ='Equity Value Creation Bridge'!D7 -> 14.766966 | C17: ='Equity Value Creation Bridge'!E7 -> 0.18899525
A18: ='Equity Value Creation Bridge'!B8 -> Multiple change | B18: ='Equity Value Creation Bridge'!D8 -> 0 | C18: ='Equity Value Creation Bridge'!E8 -> 0
A19: ='Equity Value Creation Bridge'!B9 -> Add-on purchase price (debt-funded) | B19: ='Equity Value Creation Bridge'!D9 -> -7.92 | C19: ='Equity Value Creation Bridge'!E9 -> -0.10136425
A20: ='Equity Value Creation Bridge'!B10 -> Debt paydown | B20: ='Equity Value Creation Bridge'!D10 -> 26.027881 | C20: ='Equity Value Creation Bridge'!E10 -> 0.33311825
A21: ='Equity Value Creation Bridge'!B11 -> Cash generation (retained) | B21: ='Equity Value Creation Bridge'!D11 -> 6.5069703 | C21: ='Equity Value Creation Bridge'!E11 -> 0.083279563
A22: ='Equity Value Creation Bridge'!B12 -> Exit equity value (bridge) | B22: ='Equity Value Creation Bridge'!D12 -> 110.13406
A24: Named judgment calls
A25: ID | B25: Judgment call | C25: Underwritten choice | D25: Alternative rejected | E25: Exit equity excluded vs alternative ($M) | F25: Rationale
A26: JC1 | B26: Exit multiple held at entry multiple | C26: =TEXT('Entry and Exit Assumptions'!B14,"0.0")&"x exit multiple" -> 8.0x exit multiple | D26: =TEXT('Entry and Exit Assumptions'!B15,"0.0")&"x management comp set" -> 9.5x management comp set | E26: ='Value Driver Inputs'!B12*('Entry and Exit Assumptions'!B15-'Entry and Exit Assumptions'!B14) -> 23.534851 | F26: No multiple expansion underwritten: LMM services exits are cyclical and the 9.5x comp set includes larger, more diversified peers.
A27: JC2 | B27: Margin expansion haircut | C27: ="+"&TEXT(('Value Driver Inputs'!B11-'Entry and Exit Assumptions'!B6)*10000,"0")&" bps credited" -> +200 bps credited | D27: ="+"&TEXT(('Value Driver Inputs'!B16-'Entry and Exit Assumptions'!B6)*10000,"0")&" bps management plan" -> +400 bps management plan | E27: ='Value Driver Inputs'!B10*('Value Driver Inputs'!B16-'Value Driver Inputs'!B11)*'Entry and Exit Assumptions'!B14 -> 14.766966 | F27: Only procurement and pricing actions already signed are credited; the labor-productivity half of the plan is unproven.
A28: JC3 | B28: Unsigned add-on pipeline excluded | C28: ="$"&TEXT('Value Driver Inputs'!B6,"0.0")&"M signed-LOI add-on" -> $12.0M signed-LOI add-on | D28: ="+$"&TEXT('Value Driver Inputs'!B18,"0.0")&"M unsigned pipeline" -> +$20.0M unsigned pipeline | E28: ='Value Driver Inputs'!B18*'Value Driver Inputs'!B7*('Entry and Exit Assumptions'!B14-'Value Driver Inputs'!B8) -> 6 | F28: Unsigned targets are not underwritten; excluded value is shown net of purchase price at the same add-on multiple.
A29: JC4 | B29: Cash conversion haircut | C29: =TEXT('Value Driver Inputs'!B14,"0%")&" FCF / EBITDA" -> 50% FCF / EBITDA | D29: =TEXT('Value Driver Inputs'!B17,"0%")&" management case" -> 65% management case | E29: =('Value Driver Inputs'!B17-'Value Driver Inputs'!B14)*'Value Driver Inputs'!C29 -> 9.7604554 | F29: Fleet capex catch-up in years 1-2 and higher cash taxes after the recap reduce free cash flow.
A30: Total | B30: Equity value excluded by judgment calls (approximate; effects interact, not strictly additive) | E30: =SUM(E26:E29) -> 54.062272
A32: Result
A33: Gross MOIC | B33: ='Summary Recommendation'!B7 -> 3.4416893
A34: Gross IRR | B34: ='Summary Recommendation'!B8 -> 0.28042555
A35: Downside MOIC | B35: ='Summary Recommendation'!B23 -> 2.0332646
A36: Largest lever | B36: ='Lever Impact Ranking'!B19 -> Debt paydown
A37: RECOMMENDATION | B37: ='Summary Recommendation'!B27 -> UNDERWRITE - VALUE CREATION PLAN SUPPORTS RETURNS
A38: Reasoning | B38: ='Summary Recommendation'!B28 -> Base MOIC 3.44x vs target 2.50x; IRR 28.0% vs 20.0%; operational share 68% (min 50%); multiple share 0% (max 25%); downside MOIC 2.03x (floor 1.25x).
A40: How to read this example
A41: 1. Value created comes mostly from operational levers (organic growth, the signed add-on and +200 bps margin) and from deleveraging. No multiple expansion is underwritten.
A42: 2. The judgment calls are conservative: reversing them would add the value in E26:E29. That upside is real but unproven, so it is kept out of the underwriting case.
A43: 3. The downside case (Summary Recommendation rows 16-23) cuts the exit multiple by 1.0x, halves organic growth and removes the margin gain. It is still tested against the downside MOIC floor.
